<?xml version="1.0" encoding="utf-8" ?><dwsync><file name="statistics.admin.inc" server="ftp.farsidedevelopment.com//ips/" local="3482366700" remote="318763443876739572" Dst="-1" /><file name="statistics.info" server="ftp.farsidedevelopment.com//ips/" local="3482367531" remote="318763443876739572" Dst="-1" /><file name="statistics.install" server="ftp.farsidedevelopment.com//ips/" local="3482366700" remote="318763443876739572" Dst="-1" /><file name="statistics.pages.inc" server="ftp.farsidedevelopment.com//ips/" local="3482366700" remote="318763443876739572" Dst="-1" /><file name="statistics.php" server="ftp.farsidedevelopment.com//ips/" local="3482366700" remote="318763443876739572" Dst="-1" /><file name="statistics.js" server="ftp.farsidedevelopment.com//ips/" local="3482366700" remote="318763443876739572" Dst="-1" /><file name="statistics.module" server="ftp.farsidedevelopment.com//ips/" local="3482366700" remote="318763443876739572" Dst="-1" /><file name="statistics.test" server="ftp.farsidedevelopment.com//ips/" local="3482366700" remote="318763443876739572" Dst="-1" /><file name="statistics.tokens.inc" server="ftp.farsidedevelopment.com//ips/" local="3482366700" remote="318763443876739572" Dst="-1" /></dwsync>